pyfzf/__init__.py
pyfzf/py.typed
pyfzf/__pycache__/__init__.cpython-310.pyc
pyfzf/__pycache__/pyfzf.cpython-310.pyc
pyfzf_iter-0.0.1.dist-info/LICENSE
pyfzf_iter-0.0.1.dist-info/METADATA
pyfzf_iter-0.0.1.dist-info/WHEEL
pyfzf_iter-0.0.1.dist-info/top_level.txt
pyfzf_iter-0.0.1.dist-info/RECORD
