Metadata-Version: 2.1
Name: pyfzf_iter
Version: 0.0.1
Summary: Python wrapper for junegunn's fuzzyfinder (fzf)
Home-page: https://github.com/seanbreckenridge/pyfzf
Author: Sean Breckenridge
License: MIT
Platform: UNKNOWN
Classifier: Environment :: Console
Classifier: Intended Audience :: Developers
Classifier: License :: OSI Approved :: MIT License
Classifier: Operating System :: OS Independent
Classifier: Programming Language :: Python
Classifier: Topic :: Terminals
Requires-Python: >=3.6
License-File: LICENSE
